flyt_python/__init__.py
flyt_python/daemon.py
flyt_python/flyt_python.py
flyt_python/utils.py
flyt_python/Demo Apps/__init__.py
flyt_python/Demo Apps/demo_app_1.py
flyt_python/Demo Apps/demo_app_2.py
flyt_python-0.2.3.dist-info/METADATA
flyt_python-0.2.3.dist-info/RECORD
flyt_python-0.2.3.dist-info/WHEEL
flyt_python-0.2.3.dist-info/top_level.txt
