Metadata-Version: 2.1
Name: flyt-python
Version: 0.2.3
Summary: Python package for Drone Applications
Home-page: UNKNOWN
Author: ayush_98
Author-email: ayush@flytbase.com
License: LICENSE.txt
Platform: UNKNOWN
Classifier: Programming Language :: Python :: 3.6
Classifier: Operating System :: OS Independent
Requires-Dist: redis
Requires-Dist: websocket-client (==0.50.0)
Requires-Dist: requests
